polyvers/__init__.py
polyvers/__main__.py
polyvers/bumpcmd.py
polyvers/cli.py
polyvers/engrave.py
polyvers/pvproject.py
polyvers/pvtags.py
polyvers/vermath.py
polyvers/_vendor/__init__.py
polyvers/_vendor/traitlets/__init__.py
polyvers/_vendor/traitlets/_version.py
polyvers/_vendor/traitlets/log.py
polyvers/_vendor/traitlets/traitlets.py
polyvers/_vendor/traitlets/config/__init__.py
polyvers/_vendor/traitlets/config/application.py
polyvers/_vendor/traitlets/config/configurable.py
polyvers/_vendor/traitlets/config/loader.py
polyvers/_vendor/traitlets/config/manager.py
polyvers/_vendor/traitlets/config/sphinxdoc.py
polyvers/_vendor/traitlets/utils/__init__.py
polyvers/_vendor/traitlets/utils/bunch.py
polyvers/_vendor/traitlets/utils/descriptions.py
polyvers/_vendor/traitlets/utils/getargspec.py
polyvers/_vendor/traitlets/utils/importstring.py
polyvers/_vendor/traitlets/utils/sentinel.py
polyvers/cmdlet/__init__.py
polyvers/cmdlet/autotrait.py
polyvers/cmdlet/cfgcmd.py
polyvers/cmdlet/cmdlets.py
polyvers/cmdlet/errlog.py
polyvers/cmdlet/interpctxt.py
polyvers/cmdlet/slicetrait.py
polyvers/cmdlet/traitquery.py
polyvers/cmdlet/yamlconfloader.py
polyvers/utils/__init__.py
polyvers/utils/fileutil.py
polyvers/utils/logconfutils.py
polyvers/utils/mainpump.py
polyvers/utils/oscmd.py
polyvers/utils/yamlutil.py
polyvers-0.1.1a1.dist-info/LICENSE.txt
polyvers-0.1.1a1.dist-info/METADATA
polyvers-0.1.1a1.dist-info/RECORD
polyvers-0.1.1a1.dist-info/WHEEL
polyvers-0.1.1a1.dist-info/entry_points.txt
polyvers-0.1.1a1.dist-info/top_level.txt
polyvers-0.1.1a1.dist-info/zip-safe
