Metadata-Version: 2.1
Name: polyvers
Version: 0.1.1a1
Summary: Bump sub-project versions in Git monorepos independently.
Home-page: https://github.com/jrcstu/polyvers
Author: Kostis Anagnostopoulos
Author-email: ankostis@gmail.com
License: EUPL 1.2
Download-URL: https://pypi.org/project/polyvers/
Project-URL: Documentation, https://polyvers.readthedocs.io/
Project-URL: Source, https://github.com/jrcstu/polyvers
Project-URL: Tracker, https://github.com/jrcstu/polyvers/issues
Project-URL: Polyversion, https://pypi.org/project/polyversion/
Keywords: version-management,configuration-management,versioning,git,monorepo,tool,library
Platform: any
Classifier: Development Status :: 3 - Alpha
Classifier: Intended Audience :: Developers
Classifier: License :: OSI Approved :: European Union Public Licence 1.1 (EUPL 1.1)
Classifier: Natural Language :: English
Classifier: Programming Language :: Python :: 3
Classifier: Programming Language :: Python :: 3.6
Classifier: Programming Language :: Python :: 3.7
Requires-Python: >=3.6
Provides-Extra: test
Requires-Dist: polyversion (>=0.2.0a2)
Requires-Dist: boltons
Requires-Dist: toolz
Requires-Dist: rainbow-logging-handler
Requires-Dist: ruamel.yaml
Requires-Dist: ipython-genutils
Requires-Dist: spectate
Requires-Dist: ruamel.yaml (>=0.15.37)
Requires-Dist: packaging (>=17.1)
Requires-Dist: contextvars; python_version < "3.7"
Provides-Extra: test
Requires-Dist: pytest (>=3.5.0); extra == 'test'
Requires-Dist: pytest-runner; extra == 'test'
Requires-Dist: pytest-cov; extra == 'test'
Requires-Dist: flake8; extra == 'test'
Requires-Dist: flake8-builtins; extra == 'test'
Requires-Dist: flake8-mutable; extra == 'test'
Provides-Extra: test
Requires-Dist: mypy; (python_version>="3") and extra == 'test'
